MANIFEST.in
README.md
setup.py
xztools/__init__.py
xztools/my_functions.py
xztools.egg-info/PKG-INFO
xztools.egg-info/SOURCES.txt
xztools.egg-info/dependency_links.txt
xztools.egg-info/top_level.txt